fping/__init__.py
fping/fping.py
fping-0.0.1a2.dist-info/DESCRIPTION.rst
fping-0.0.1a2.dist-info/METADATA
fping-0.0.1a2.dist-info/RECORD
fping-0.0.1a2.dist-info/WHEEL
fping-0.0.1a2.dist-info/metadata.json
fping-0.0.1a2.dist-info/top_level.txt
